yamld/__init__.py
yamld/common.py
yamld/parser.py
yamld/with_iofile.py
yamld/with_pandas.py
yamld/writer.py
yamld-0.0.33.data/scripts/csv2yamld
yamld-0.0.33.data/scripts/yamld
yamld-0.0.33.data/scripts/yamld2csv
yamld-0.0.33.dist-info/METADATA
yamld-0.0.33.dist-info/WHEEL
yamld-0.0.33.dist-info/top_level.txt
yamld-0.0.33.dist-info/RECORD
