Metadata-Version: 2.1
Name: yamld
Version: 0.0.33
Summary: parser of YAMLd, a tiny subset of YAML
Home-page: https://github.com/badranx/yaml-datasets
Author: Yahya Badran
Author-email: techtweaking@gmail.com
License: MIT
Classifier: Programming Language :: Python :: 3
Classifier: License :: OSI Approved :: MIT License
Classifier: Operating System :: OS Independent
Requires-Dist: pandas >=1.0.0
